{
  "blurhash": "UOHB*s-T?^MxTKju%MR*IpIpWANGD%WYRPV@",
  "fileName": "IMG_20180901_150649.jpg",
  "exifData": {
    "Make": "OnePlus",
    "Model": "ONEPLUS A3000",
    "XResolution": 72,
    "YResolution": 72,
    "ResolutionUnit": 2,
    "Software": "OnePlus3-user 8.0.0 OPR1.170623.032 1808161403 release-keys",
    "ModifyDate": 1535814409,
    "YCbCrPositioning": 1,
    "GPSVersionID": [
      2,
      2,
      0,
      0
    ],
    "GPSLatitudeRef": "N",
    "GPSLatitude": 42.796808999999996,
    "GPSLongitudeRef": "W",
    "GPSLongitude": -84.61212422222222,
    "GPSAltitudeRef": 2,
    "GPSAltitude": 227,
    "GPSTimeStamp": [
      19,
      6,
      49
    ],
    "GPSDateStamp": "2018:09:01",
    "ExposureTime": 0.058823529411764705,
    "FNumber": 2,
    "ExposureProgram": 0,
    "ISO": 2000,
    "DateTimeOriginal": 1535814409,
    "CreateDate": 1535814409,
    "ShutterSpeedValue": 4.058,
    "ApertureValue": 2,
    "BrightnessValue": 3,
    "MeteringMode": 3,
    "Flash": 16,
    "FocalLength": 4.26,
    "SubSecTime": "313524",
    "SubSecTimeOriginal": "313524",
    "SubSecTimeDigitized": "313524",
    "ColorSpace": 1,
    "ExifImageWidth": 3480,
    "ExifImageHeight": 4640,
    "SensingMethod": 2,
    "ExposureMode": 0,
    "WhiteBalance": 0,
    "FocalLengthIn35mmFormat": 28,
    "ImageUniqueID": "93bdd2c570e84e4f0000000000000000",
    "InteropIndex": "R98"
  },
  "createdDate": "2018-09-01T15:06:49.000Z",
  "width": 3480,
  "height": 4640
}