{
  "blurhash": "UHE.-Cxwx[4n%jS%NaR*?bWXtlbI%LWBx]oz",
  "fileName": "PXL_20210312_221810879.jpg",
  "exifData": {
    "ImageWidth": 4032,
    "ImageHeight": 3024,
    "Make": "Google",
    "Model": "Pixel 4 XL",
    "Orientation": 3,
    "XResolution": 72,
    "YResolution": 72,
    "ResolutionUnit": 2,
    "Software": "HDR+ 1.0.352609463zd",
    "ModifyDate": 1615569490,
    "YCbCrPositioning": 1,
    "GPSVersionID": [
      2,
      2,
      0,
      0
    ],
    "GPSLatitudeRef": "N",
    "GPSLatitude": 42.73677222222222,
    "GPSLongitudeRef": "W",
    "GPSLongitude": -84.74437777777779,
    "GPSAltitudeRef": 0,
    "GPSAltitude": 229.96,
    "GPSTimeStamp": [
      22,
      18,
      10
    ],
    "GPSDOP": 30,
    "GPSImgDirectionRef": "M",
    "GPSImgDirection": 310,
    "GPSDateStamp": "2021:03:12",
    "ExposureTime": 0.041663,
    "FNumber": 2.4,
    "ExposureProgram": 2,
    "ISO": 76,
    "DateTimeOriginal": 1615569490,
    "CreateDate": 1615569490,
    "undefined": "-05:00",
    "ShutterSpeedValue": 4.59,
    "ApertureValue": 2.53,
    "BrightnessValue": 2.51,
    "ExposureCompensation": 0,
    "MaxApertureValue": 2.53,
    "SubjectDistance": 2.944,
    "MeteringMode": 2,
    "Flash": 16,
    "FocalLength": 5.84,
    "SubSecTime": "912198",
    "SubSecTimeOriginal": "912198",
    "SubSecTimeDigitized": "912198",
    "ColorSpace": 1,
    "ExifImageWidth": 4032,
    "ExifImageHeight": 3024,
    "SensingMethod": 2,
    "CustomRendered": 1,
    "ExposureMode": 0,
    "WhiteBalance": 0,
    "DigitalZoomRatio": 1.49,
    "FocalLengthIn35mmFormat": 43,
    "SceneCaptureType": 0,
    "Contrast": 0,
    "Saturation": 0,
    "Sharpness": 0,
    "SubjectDistanceRange": 2,
    "InteropIndex": "R98"
  },
  "createdDate": "2021-03-12T17:18:10.000Z",
  "width": 4032,
  "height": 3024
}