{
  "blurhash": "UNCQ0+00~qD%_3Di.8IU%NWXt7Rjax%MWBoL",
  "fileName": "PXL_20211226_144409881.jpg",
  "exifData": {
    "ImageWidth": 3072,
    "ImageHeight": 4080,
    "Make": "Google",
    "Model": "Pixel 6 Pro",
    "Orientation": 1,
    "XResolution": 72,
    "YResolution": 72,
    "ResolutionUnit": 2,
    "Software": "HDR+ 1.0.414775603zd",
    "ModifyDate": 1640511849,
    "YCbCrPositioning": 1,
    "GPSLatitudeRef": "N",
    "GPSLatitude": 42.73676944444445,
    "GPSLongitudeRef": "W",
    "GPSLongitude": -84.74440833333334,
    "GPSAltitudeRef": 0,
    "GPSAltitude": 230.29,
    "GPSTimeStamp": [
      14,
      43,
      36
    ],
    "GPSImgDirectionRef": "M",
    "GPSImgDirection": 232,
    "GPSDateStamp": "2021:12:26",
    "ExposureTime": 0.011484,
    "FNumber": 1.85,
    "ExposureProgram": 2,
    "ISO": 425,
    "DateTimeOriginal": 1640511849,
    "CreateDate": 1640511849,
    "undefined": "-05:00",
    "ShutterSpeedValue": 6.44,
    "ApertureValue": 1.78,
    "BrightnessValue": 1.13,
    "ExposureCompensation": 0,
    "MaxApertureValue": 1.78,
    "SubjectDistance": 0.228,
    "MeteringMode": 2,
    "Flash": 16,
    "FocalLength": 6.81,
    "SubSecTime": "881",
    "SubSecTimeOriginal": "881",
    "SubSecTimeDigitized": "881",
    "ColorSpace": 1,
    "ExifImageWidth": 3072,
    "ExifImageHeight": 4080,
    "SensingMethod": 2,
    "CustomRendered": 1,
    "ExposureMode": 0,
    "WhiteBalance": 0,
    "DigitalZoomRatio": 0,
    "FocalLengthIn35mmFormat": 24,
    "SceneCaptureType": 0,
    "Contrast": 0,
    "Saturation": 0,
    "Sharpness": 0,
    "SubjectDistanceRange": 1,
    "LensMake": "Google",
    "LensModel": "Pixel 6 Pro back camera 6.81mm f/1.85",
    "InteropIndex": "R98"
  },
  "createdDate": "2021-12-26T09:44:09.000Z",
  "width": 3072,
  "height": 4080
}